{
	"id": "2FfIbq2WXtAmtgH",
	"json": "{\"id\":\"2FfIbq2WXtAmtgH\",\"url\":\"https://juejin.cn/post/7271205668840767547\",\"uniqueKey\":\"https://juejin.cn/post/7271205668840767547\",\"method\":\"GET\",\"noRetry\":false,\"retryCount\":0,\"errorMessages\":[],\"headers\":{},\"userData\":{\"label\":\"DETAIL\",\"__crawlee\":{\"enqueueStrategy\":\"same-hostname\"}}}",
	"method": "GET",
	"orderNo": 1729738012207,
	"retryCount": 0,
	"uniqueKey": "https://juejin.cn/post/7271205668840767547",
	"url": "https://juejin.cn/post/7271205668840767547"
}