{
	"id": "2rkUDhKYhvp1zYi",
	"json": "{\"id\":\"2rkUDhKYhvp1zYi\",\"url\":\"https://juejin.cn/post/6844903633176231943\",\"uniqueKey\":\"https://juejin.cn/post/6844903633176231943\",\"method\":\"GET\",\"noRetry\":false,\"retryCount\":0,\"errorMessages\":[],\"headers\":{},\"userData\":{\"label\":\"DETAIL\",\"__crawlee\":{\"enqueueStrategy\":\"same-hostname\"}}}",
	"method": "GET",
	"orderNo": 1729706471019,
	"retryCount": 0,
	"uniqueKey": "https://juejin.cn/post/6844903633176231943",
	"url": "https://juejin.cn/post/6844903633176231943"
}