{
	"id": "3A8jYomeYjIFzz0",
	"json": "{\"id\":\"3A8jYomeYjIFzz0\",\"url\":\"https://juejin.cn/post/7357957599844057088\",\"uniqueKey\":\"https://juejin.cn/post/7357957599844057088\",\"method\":\"GET\",\"noRetry\":false,\"retryCount\":0,\"errorMessages\":[],\"headers\":{},\"userData\":{\"label\":\"DETAIL\",\"__crawlee\":{\"enqueueStrategy\":\"same-hostname\"}}}",
	"method": "GET",
	"orderNo": 1729787801270,
	"retryCount": 0,
	"uniqueKey": "https://juejin.cn/post/7357957599844057088",
	"url": "https://juejin.cn/post/7357957599844057088"
}