{
	"id": "3QZBPbVUHrS1iwC",
	"json": "{\"id\":\"3QZBPbVUHrS1iwC\",\"url\":\"https://juejin.cn/post/6844903461453037576\",\"uniqueKey\":\"https://juejin.cn/post/6844903461453037576\",\"method\":\"GET\",\"noRetry\":false,\"retryCount\":0,\"errorMessages\":[],\"headers\":{},\"userData\":{\"label\":\"DETAIL\",\"__crawlee\":{\"enqueueStrategy\":\"same-hostname\"}}}",
	"method": "GET",
	"orderNo": 1729738011473,
	"retryCount": 0,
	"uniqueKey": "https://juejin.cn/post/6844903461453037576",
	"url": "https://juejin.cn/post/6844903461453037576"
}