{
	"id": "50OiLhDlErbp6xV",
	"json": "{\"id\":\"50OiLhDlErbp6xV\",\"url\":\"https://juejin.cn/post/7375858343179255862\",\"uniqueKey\":\"https://juejin.cn/post/7375858343179255862\",\"method\":\"GET\",\"noRetry\":false,\"retryCount\":0,\"errorMessages\":[],\"headers\":{},\"userData\":{\"label\":\"DETAIL\",\"__crawlee\":{\"enqueueStrategy\":\"same-hostname\"}}}",
	"method": "GET",
	"orderNo": 1729787799782,
	"retryCount": 0,
	"uniqueKey": "https://juejin.cn/post/7375858343179255862",
	"url": "https://juejin.cn/post/7375858343179255862"
}