{
	"id": "5yZnZOyHChe036n",
	"json": "{\"id\":\"5yZnZOyHChe036n\",\"url\":\"https://juejin.cn/post/6893435960705417224\",\"uniqueKey\":\"https://juejin.cn/post/6893435960705417224\",\"method\":\"GET\",\"noRetry\":false,\"retryCount\":0,\"errorMessages\":[],\"headers\":{},\"userData\":{\"label\":\"DETAIL\",\"__crawlee\":{\"enqueueStrategy\":\"same-hostname\"}}}",
	"method": "GET",
	"orderNo": 1729791909048,
	"retryCount": 0,
	"uniqueKey": "https://juejin.cn/post/6893435960705417224",
	"url": "https://juejin.cn/post/6893435960705417224"
}