{
	"id": "6eG8A3QVCcvABMi",
	"json": "{\"id\":\"6eG8A3QVCcvABMi\",\"url\":\"https://juejin.cn/post/6885957893724569613\",\"uniqueKey\":\"https://juejin.cn/post/6885957893724569613\",\"method\":\"GET\",\"noRetry\":false,\"retryCount\":0,\"errorMessages\":[],\"headers\":{},\"userData\":{\"label\":\"DETAIL\",\"__crawlee\":{\"enqueueStrategy\":\"same-hostname\"}}}",
	"method": "GET",
	"orderNo": 1729706468449,
	"retryCount": 0,
	"uniqueKey": "https://juejin.cn/post/6885957893724569613",
	"url": "https://juejin.cn/post/6885957893724569613"
}