{
	"id": "BG4NgVF1m0JssbV",
	"json": "{\"id\":\"BG4NgVF1m0JssbV\",\"url\":\"https://juejin.cn/post/7018708834948481031\",\"uniqueKey\":\"https://juejin.cn/post/7018708834948481031\",\"method\":\"GET\",\"noRetry\":false,\"retryCount\":0,\"errorMessages\":[],\"headers\":{},\"userData\":{\"label\":\"DETAIL\",\"__crawlee\":{\"enqueueStrategy\":\"same-hostname\"}}}",
	"method": "GET",
	"orderNo": 1729738012013,
	"retryCount": 0,
	"uniqueKey": "https://juejin.cn/post/7018708834948481031",
	"url": "https://juejin.cn/post/7018708834948481031"
}