{
	"id": "bmi1rS3KGh3dGu9",
	"json": "{\"id\":\"bmi1rS3KGh3dGu9\",\"url\":\"https://juejin.cn/post/7356485240804196406\",\"uniqueKey\":\"https://juejin.cn/post/7356485240804196406\",\"method\":\"GET\",\"noRetry\":false,\"retryCount\":0,\"errorMessages\":[],\"headers\":{},\"userData\":{\"label\":\"DETAIL\",\"__crawlee\":{\"enqueueStrategy\":\"same-hostname\"}}}",
	"method": "GET",
	"orderNo": 1729738011107,
	"retryCount": 0,
	"uniqueKey": "https://juejin.cn/post/7356485240804196406",
	"url": "https://juejin.cn/post/7356485240804196406"
}