{
	"id": "byeIkhxmioqJZcs",
	"json": "{\"id\":\"byeIkhxmioqJZcs\",\"url\":\"https://juejin.cn/post/6844903824235167751\",\"uniqueKey\":\"https://juejin.cn/post/6844903824235167751\",\"method\":\"GET\",\"noRetry\":false,\"retryCount\":0,\"errorMessages\":[],\"headers\":{},\"userData\":{\"label\":\"DETAIL\",\"__crawlee\":{\"enqueueStrategy\":\"same-hostname\"}}}",
	"method": "GET",
	"orderNo": 1729738012326,
	"retryCount": 0,
	"uniqueKey": "https://juejin.cn/post/6844903824235167751",
	"url": "https://juejin.cn/post/6844903824235167751"
}