{
	"id": "CBaGr9VQuwYcLpd",
	"json": "{\"id\":\"CBaGr9VQuwYcLpd\",\"url\":\"https://juejin.cn/post/7177292555283857468\",\"loadedUrl\":\"https://juejin.cn/post/7177292555283857468\",\"uniqueKey\":\"https://juejin.cn/post/7177292555283857468\",\"method\":\"GET\",\"noRetry\":false,\"retryCount\":0,\"errorMessages\":[],\"headers\":{},\"userData\":{\"label\":\"DETAIL\",\"__crawlee\":{\"enqueueStrategy\":\"same-hostname\",\"state\":4}},\"handledAt\":\"2024-10-24T19:03:59.332Z\"}",
	"method": "GET",
	"orderNo": null,
	"retryCount": 0,
	"uniqueKey": "https://juejin.cn/post/7177292555283857468",
	"url": "https://juejin.cn/post/7177292555283857468"
}