{
	"id": "CHzxh0lqT4CMCXO",
	"json": "{\"id\":\"CHzxh0lqT4CMCXO\",\"url\":\"https://juejin.cn/post/6955659229311008781\",\"loadedUrl\":\"https://juejin.cn/post/6955659229311008781\",\"uniqueKey\":\"https://juejin.cn/post/6955659229311008781\",\"method\":\"GET\",\"noRetry\":false,\"retryCount\":0,\"errorMessages\":[],\"headers\":{},\"userData\":{\"label\":\"DETAIL\",\"__crawlee\":{\"enqueueStrategy\":\"same-hostname\",\"state\":4}},\"handledAt\":\"2024-10-23T18:13:03.872Z\"}",
	"method": "GET",
	"orderNo": null,
	"retryCount": 0,
	"uniqueKey": "https://juejin.cn/post/6955659229311008781",
	"url": "https://juejin.cn/post/6955659229311008781"
}