{
	"id": "eHu2F9n51jTsuwK",
	"json": "{\"id\":\"eHu2F9n51jTsuwK\",\"url\":\"https://juejin.cn/post/6844904079693447175\",\"uniqueKey\":\"https://juejin.cn/post/6844904079693447175\",\"method\":\"GET\",\"noRetry\":false,\"retryCount\":0,\"errorMessages\":[],\"headers\":{},\"userData\":{\"label\":\"DETAIL\",\"__crawlee\":{\"enqueueStrategy\":\"same-hostname\"}}}",
	"method": "GET",
	"orderNo": 1729706479554,
	"retryCount": 0,
	"uniqueKey": "https://juejin.cn/post/6844904079693447175",
	"url": "https://juejin.cn/post/6844904079693447175"
}