{
	"id": "eMxLFKh9aE9oy4i",
	"json": "{\"id\":\"eMxLFKh9aE9oy4i\",\"url\":\"https://juejin.cn/post/7419958371448438825\",\"uniqueKey\":\"https://juejin.cn/post/7419958371448438825\",\"method\":\"GET\",\"noRetry\":false,\"retryCount\":0,\"errorMessages\":[],\"headers\":{},\"userData\":{\"label\":\"DETAIL\",\"__crawlee\":{\"enqueueStrategy\":\"same-hostname\"}}}",
	"method": "GET",
	"orderNo": 1729791914422,
	"retryCount": 0,
	"uniqueKey": "https://juejin.cn/post/7419958371448438825",
	"url": "https://juejin.cn/post/7419958371448438825"
}