{
	"id": "eS8R06DuQlQLY0l",
	"json": "{\"id\":\"eS8R06DuQlQLY0l\",\"url\":\"https://juejin.cn/post/7239742600550350906\",\"uniqueKey\":\"https://juejin.cn/post/7239742600550350906\",\"method\":\"GET\",\"noRetry\":false,\"retryCount\":0,\"errorMessages\":[],\"headers\":{},\"userData\":{\"label\":\"DETAIL\",\"__crawlee\":{\"enqueueStrategy\":\"same-hostname\"}}}",
	"method": "GET",
	"orderNo": 1729791903808,
	"retryCount": 0,
	"uniqueKey": "https://juejin.cn/post/7239742600550350906",
	"url": "https://juejin.cn/post/7239742600550350906"
}