{
	"id": "FLtTD2rzVqGkcdM",
	"json": "{\"id\":\"FLtTD2rzVqGkcdM\",\"url\":\"https://juejin.cn/post/6920457735955972104\",\"uniqueKey\":\"https://juejin.cn/post/6920457735955972104\",\"method\":\"GET\",\"noRetry\":false,\"retryCount\":0,\"errorMessages\":[],\"headers\":{},\"userData\":{\"label\":\"DETAIL\",\"__crawlee\":{\"enqueueStrategy\":\"same-hostname\"}}}",
	"method": "GET",
	"orderNo": 1729791909165,
	"retryCount": 0,
	"uniqueKey": "https://juejin.cn/post/6920457735955972104",
	"url": "https://juejin.cn/post/6920457735955972104"
}