{
	"id": "FRdvDkW1A7nRAOv",
	"json": "{\"id\":\"FRdvDkW1A7nRAOv\",\"url\":\"https://juejin.cn/post/6844904192247595022\",\"uniqueKey\":\"https://juejin.cn/post/6844904192247595022\",\"method\":\"GET\",\"noRetry\":false,\"retryCount\":0,\"errorMessages\":[],\"headers\":{},\"userData\":{\"label\":\"DETAIL\",\"__crawlee\":{\"enqueueStrategy\":\"same-hostname\"}}}",
	"method": "GET",
	"orderNo": 1729791911901,
	"retryCount": 0,
	"uniqueKey": "https://juejin.cn/post/6844904192247595022",
	"url": "https://juejin.cn/post/6844904192247595022"
}