{
	"id": "HIID4iDPsgialv1",
	"json": "{\"id\":\"HIID4iDPsgialv1\",\"url\":\"https://juejin.cn/post/6844903743796822024\",\"uniqueKey\":\"https://juejin.cn/post/6844903743796822024\",\"method\":\"GET\",\"noRetry\":false,\"retryCount\":0,\"errorMessages\":[],\"headers\":{},\"userData\":{\"label\":\"DETAIL\",\"__crawlee\":{\"enqueueStrategy\":\"same-hostname\"}}}",
	"method": "GET",
	"orderNo": 1729706477381,
	"retryCount": 0,
	"uniqueKey": "https://juejin.cn/post/6844903743796822024",
	"url": "https://juejin.cn/post/6844903743796822024"
}