{
	"id": "hucdtlqrW254Pa5",
	"json": "{\"id\":\"hucdtlqrW254Pa5\",\"url\":\"https://juejin.cn/post/7359225201283301414\",\"loadedUrl\":\"https://juejin.cn/post/7359225201283301414\",\"uniqueKey\":\"https://juejin.cn/post/7359225201283301414\",\"method\":\"GET\",\"noRetry\":false,\"retryCount\":0,\"errorMessages\":[],\"headers\":{},\"userData\":{\"label\":\"DETAIL\",\"__crawlee\":{\"enqueueStrategy\":\"same-hostname\",\"state\":4}},\"handledAt\":\"2024-10-24T19:15:58.773Z\"}",
	"method": "GET",
	"orderNo": null,
	"retryCount": 0,
	"uniqueKey": "https://juejin.cn/post/7359225201283301414",
	"url": "https://juejin.cn/post/7359225201283301414"
}