{
	"id": "IqiZ2x39sG8IFNm",
	"json": "{\"id\":\"IqiZ2x39sG8IFNm\",\"url\":\"https://juejin.cn/post/7001063244559286303\",\"uniqueKey\":\"https://juejin.cn/post/7001063244559286303\",\"method\":\"GET\",\"noRetry\":false,\"retryCount\":0,\"errorMessages\":[],\"headers\":{},\"userData\":{\"label\":\"DETAIL\",\"__crawlee\":{\"enqueueStrategy\":\"same-hostname\"}}}",
	"method": "GET",
	"orderNo": 1729706468413,
	"retryCount": 0,
	"uniqueKey": "https://juejin.cn/post/7001063244559286303",
	"url": "https://juejin.cn/post/7001063244559286303"
}