{
	"id": "k4PVzK4JTxNlRjk",
	"json": "{\"id\":\"k4PVzK4JTxNlRjk\",\"url\":\"https://juejin.cn/post/6933404665077825549\",\"loadedUrl\":\"https://juejin.cn/post/6933404665077825549\",\"uniqueKey\":\"https://juejin.cn/post/6933404665077825549\",\"method\":\"GET\",\"noRetry\":false,\"retryCount\":0,\"errorMessages\":[],\"headers\":{},\"userData\":{\"label\":\"DETAIL\",\"__crawlee\":{\"enqueueStrategy\":\"same-hostname\",\"state\":4}},\"handledAt\":\"2024-10-23T18:10:14.201Z\"}",
	"method": "GET",
	"orderNo": null,
	"retryCount": 0,
	"uniqueKey": "https://juejin.cn/post/6933404665077825549",
	"url": "https://juejin.cn/post/6933404665077825549"
}