{
	"id": "KCAJwfnWr0k7HDG",
	"json": "{\"id\":\"KCAJwfnWr0k7HDG\",\"url\":\"https://juejin.cn/post/6850418108193390599\",\"uniqueKey\":\"https://juejin.cn/post/6850418108193390599\",\"method\":\"GET\",\"noRetry\":false,\"retryCount\":0,\"errorMessages\":[],\"headers\":{},\"userData\":{\"label\":\"DETAIL\",\"__crawlee\":{\"enqueueStrategy\":\"same-hostname\"}}}",
	"method": "GET",
	"orderNo": 1729738012131,
	"retryCount": 0,
	"uniqueKey": "https://juejin.cn/post/6850418108193390599",
	"url": "https://juejin.cn/post/6850418108193390599"
}