{
	"id": "ke6OBYeIAob2Y1d",
	"json": "{\"id\":\"ke6OBYeIAob2Y1d\",\"url\":\"https://juejin.cn/post/7379865729024131084\",\"uniqueKey\":\"https://juejin.cn/post/7379865729024131084\",\"method\":\"GET\",\"noRetry\":false,\"retryCount\":0,\"errorMessages\":[],\"headers\":{},\"userData\":{\"label\":\"DETAIL\",\"__crawlee\":{\"enqueueStrategy\":\"same-hostname\"}}}",
	"method": "GET",
	"orderNo": 1729787800251,
	"retryCount": 0,
	"uniqueKey": "https://juejin.cn/post/7379865729024131084",
	"url": "https://juejin.cn/post/7379865729024131084"
}