{
	"id": "KlW88fCPyHdyYrv",
	"json": "{\"id\":\"KlW88fCPyHdyYrv\",\"url\":\"https://juejin.cn/post/6956399640484773901\",\"uniqueKey\":\"https://juejin.cn/post/6956399640484773901\",\"method\":\"GET\",\"noRetry\":false,\"retryCount\":0,\"errorMessages\":[],\"headers\":{},\"userData\":{\"label\":\"DETAIL\",\"__crawlee\":{\"enqueueStrategy\":\"same-hostname\"}}}",
	"method": "GET",
	"orderNo": 1729706473256,
	"retryCount": 0,
	"uniqueKey": "https://juejin.cn/post/6956399640484773901",
	"url": "https://juejin.cn/post/6956399640484773901"
}