{
	"id": "lhRaBZFqxb3DtgI",
	"json": "{\"id\":\"lhRaBZFqxb3DtgI\",\"url\":\"https://juejin.cn/post/6979480649212100622\",\"uniqueKey\":\"https://juejin.cn/post/6979480649212100622\",\"method\":\"GET\",\"noRetry\":false,\"retryCount\":0,\"errorMessages\":[],\"headers\":{},\"userData\":{\"label\":\"DETAIL\",\"__crawlee\":{\"enqueueStrategy\":\"same-hostname\"}}}",
	"method": "GET",
	"orderNo": 1729706472683,
	"retryCount": 0,
	"uniqueKey": "https://juejin.cn/post/6979480649212100622",
	"url": "https://juejin.cn/post/6979480649212100622"
}