{
	"id": "lVqDU2vUeb7310c",
	"json": "{\"id\":\"lVqDU2vUeb7310c\",\"url\":\"https://juejin.cn/post/6844903879755186183\",\"loadedUrl\":\"https://juejin.cn/post/6844903879755186183\",\"uniqueKey\":\"https://juejin.cn/post/6844903879755186183\",\"method\":\"GET\",\"noRetry\":false,\"retryCount\":0,\"errorMessages\":[],\"headers\":{},\"userData\":{\"label\":\"DETAIL\",\"__crawlee\":{\"enqueueStrategy\":\"same-hostname\",\"state\":4}},\"handledAt\":\"2024-10-24T18:00:59.647Z\"}",
	"method": "GET",
	"orderNo": null,
	"retryCount": 0,
	"uniqueKey": "https://juejin.cn/post/6844903879755186183",
	"url": "https://juejin.cn/post/6844903879755186183"
}