{
	"id": "M8b4YHRyL9Zw66g",
	"json": "{\"id\":\"M8b4YHRyL9Zw66g\",\"url\":\"https://juejin.cn/post/6908584062214995981\",\"uniqueKey\":\"https://juejin.cn/post/6908584062214995981\",\"method\":\"GET\",\"noRetry\":false,\"retryCount\":0,\"errorMessages\":[],\"headers\":{},\"userData\":{\"label\":\"DETAIL\",\"__crawlee\":{\"enqueueStrategy\":\"same-hostname\"}}}",
	"method": "GET",
	"orderNo": 1729787800054,
	"retryCount": 0,
	"uniqueKey": "https://juejin.cn/post/6908584062214995981",
	"url": "https://juejin.cn/post/6908584062214995981"
}