{
	"id": "mzuRnuUeRrcne7v",
	"json": "{\"id\":\"mzuRnuUeRrcne7v\",\"url\":\"https://juejin.cn/post/6844903830572924936\",\"uniqueKey\":\"https://juejin.cn/post/6844903830572924936\",\"method\":\"GET\",\"noRetry\":false,\"retryCount\":0,\"errorMessages\":[],\"headers\":{},\"userData\":{\"label\":\"DETAIL\",\"__crawlee\":{\"enqueueStrategy\":\"same-hostname\"}}}",
	"method": "GET",
	"orderNo": 1729706477678,
	"retryCount": 0,
	"uniqueKey": "https://juejin.cn/post/6844903830572924936",
	"url": "https://juejin.cn/post/6844903830572924936"
}