{
	"id": "nOTNHrhCWBQCYYT",
	"json": "{\"id\":\"nOTNHrhCWBQCYYT\",\"url\":\"https://juejin.cn/post/6844903678617354248\",\"uniqueKey\":\"https://juejin.cn/post/6844903678617354248\",\"method\":\"GET\",\"noRetry\":false,\"retryCount\":0,\"errorMessages\":[],\"headers\":{},\"userData\":{\"label\":\"DETAIL\",\"__crawlee\":{\"enqueueStrategy\":\"same-hostname\"}}}",
	"method": "GET",
	"orderNo": 1729706471008,
	"retryCount": 0,
	"uniqueKey": "https://juejin.cn/post/6844903678617354248",
	"url": "https://juejin.cn/post/6844903678617354248"
}