{
	"id": "Og13FB6GPaJHmhx",
	"json": "{\"id\":\"Og13FB6GPaJHmhx\",\"url\":\"https://juejin.cn/post/6854573204309180423\",\"loadedUrl\":\"https://juejin.cn/post/6854573204309180423\",\"uniqueKey\":\"https://juejin.cn/post/6854573204309180423\",\"method\":\"GET\",\"noRetry\":false,\"retryCount\":0,\"errorMessages\":[],\"headers\":{},\"userData\":{\"label\":\"DETAIL\",\"__crawlee\":{\"enqueueStrategy\":\"same-hostname\",\"state\":4}},\"handledAt\":\"2024-10-23T18:16:45.809Z\"}",
	"method": "GET",
	"orderNo": null,
	"retryCount": 0,
	"uniqueKey": "https://juejin.cn/post/6854573204309180423",
	"url": "https://juejin.cn/post/6854573204309180423"
}