{
	"id": "OPPd5wASSUX6jxW",
	"json": "{\"id\":\"OPPd5wASSUX6jxW\",\"url\":\"https://juejin.cn/post/6844903960424218631\",\"uniqueKey\":\"https://juejin.cn/post/6844903960424218631\",\"method\":\"GET\",\"noRetry\":false,\"retryCount\":0,\"errorMessages\":[],\"headers\":{},\"userData\":{\"label\":\"DETAIL\",\"__crawlee\":{\"enqueueStrategy\":\"same-hostname\"}}}",
	"method": "GET",
	"orderNo": 1729706474823,
	"retryCount": 0,
	"uniqueKey": "https://juejin.cn/post/6844903960424218631",
	"url": "https://juejin.cn/post/6844903960424218631"
}