{
	"id": "pmWETsloE7MUE73",
	"json": "{\"id\":\"pmWETsloE7MUE73\",\"url\":\"https://juejin.cn/post/7317153361281908748\",\"loadedUrl\":\"https://juejin.cn/post/7317153361281908748\",\"uniqueKey\":\"https://juejin.cn/post/7317153361281908748\",\"method\":\"GET\",\"noRetry\":false,\"retryCount\":0,\"errorMessages\":[],\"headers\":{},\"userData\":{\"label\":\"DETAIL\",\"__crawlee\":{\"enqueueStrategy\":\"same-hostname\",\"state\":4}},\"handledAt\":\"2024-10-24T18:59:23.970Z\"}",
	"method": "GET",
	"orderNo": null,
	"retryCount": 0,
	"uniqueKey": "https://juejin.cn/post/7317153361281908748",
	"url": "https://juejin.cn/post/7317153361281908748"
}