{
	"id": "rg3Pwy4XEpXgi1Y",
	"json": "{\"id\":\"rg3Pwy4XEpXgi1Y\",\"url\":\"https://juejin.cn/post/6844903702105423879\",\"uniqueKey\":\"https://juejin.cn/post/6844903702105423879\",\"method\":\"GET\",\"noRetry\":false,\"retryCount\":0,\"errorMessages\":[],\"headers\":{},\"userData\":{\"label\":\"DETAIL\",\"__crawlee\":{\"enqueueStrategy\":\"same-hostname\"}}}",
	"method": "GET",
	"orderNo": 1729706475458,
	"retryCount": 0,
	"uniqueKey": "https://juejin.cn/post/6844903702105423879",
	"url": "https://juejin.cn/post/6844903702105423879"
}