{
	"id": "sV1joMleppiCDx9",
	"json": "{\"id\":\"sV1joMleppiCDx9\",\"url\":\"https://juejin.cn/post/6906021856210321422\",\"loadedUrl\":\"https://juejin.cn/post/6906021856210321422\",\"uniqueKey\":\"https://juejin.cn/post/6906021856210321422\",\"method\":\"GET\",\"noRetry\":false,\"retryCount\":0,\"errorMessages\":[],\"headers\":{},\"userData\":{\"label\":\"DETAIL\",\"__crawlee\":{\"enqueueStrategy\":\"same-hostname\",\"state\":4}},\"handledAt\":\"2024-10-23T18:13:44.738Z\"}",
	"method": "GET",
	"orderNo": null,
	"retryCount": 0,
	"uniqueKey": "https://juejin.cn/post/6906021856210321422",
	"url": "https://juejin.cn/post/6906021856210321422"
}