{
	"id": "UC02kTk7BBOaCEB",
	"json": "{\"id\":\"UC02kTk7BBOaCEB\",\"url\":\"https://juejin.cn/post/7147602740405862407\",\"loadedUrl\":\"https://juejin.cn/post/7147602740405862407\",\"uniqueKey\":\"https://juejin.cn/post/7147602740405862407\",\"method\":\"GET\",\"noRetry\":false,\"retryCount\":0,\"errorMessages\":[],\"headers\":{},\"userData\":{\"label\":\"DETAIL\",\"__crawlee\":{\"enqueueStrategy\":\"same-hostname\",\"state\":4}},\"handledAt\":\"2024-10-24T18:24:53.055Z\"}",
	"method": "GET",
	"orderNo": null,
	"retryCount": 0,
	"uniqueKey": "https://juejin.cn/post/7147602740405862407",
	"url": "https://juejin.cn/post/7147602740405862407"
}