{
	"id": "vDmUgeySR0sF4hC",
	"json": "{\"id\":\"vDmUgeySR0sF4hC\",\"url\":\"https://juejin.cn/post/7411429674105258023\",\"uniqueKey\":\"https://juejin.cn/post/7411429674105258023\",\"method\":\"GET\",\"noRetry\":false,\"retryCount\":0,\"errorMessages\":[],\"headers\":{},\"userData\":{\"label\":\"DETAIL\",\"__crawlee\":{\"enqueueStrategy\":\"same-hostname\"}}}",
	"method": "GET",
	"orderNo": 1729787801392,
	"retryCount": 0,
	"uniqueKey": "https://juejin.cn/post/7411429674105258023",
	"url": "https://juejin.cn/post/7411429674105258023"
}