{
	"id": "VzCOBgM0JOFhT0x",
	"json": "{\"id\":\"VzCOBgM0JOFhT0x\",\"url\":\"https://juejin.cn/post/7346121373112254527\",\"loadedUrl\":\"https://juejin.cn/post/7346121373112254527\",\"uniqueKey\":\"https://juejin.cn/post/7346121373112254527\",\"method\":\"GET\",\"noRetry\":false,\"retryCount\":0,\"errorMessages\":[],\"headers\":{},\"userData\":{\"label\":\"DETAIL\",\"__crawlee\":{\"enqueueStrategy\":\"same-hostname\",\"state\":4}},\"handledAt\":\"2024-10-23T18:17:29.531Z\"}",
	"method": "GET",
	"orderNo": null,
	"retryCount": 0,
	"uniqueKey": "https://juejin.cn/post/7346121373112254527",
	"url": "https://juejin.cn/post/7346121373112254527"
}