{
	"id": "x5HPGLdCAllesrE",
	"json": "{\"id\":\"x5HPGLdCAllesrE\",\"url\":\"https://juejin.cn/post/7389137198782349364\",\"uniqueKey\":\"https://juejin.cn/post/7389137198782349364\",\"method\":\"GET\",\"noRetry\":false,\"retryCount\":0,\"errorMessages\":[],\"headers\":{},\"userData\":{\"label\":\"DETAIL\",\"__crawlee\":{\"enqueueStrategy\":\"same-hostname\"}}}",
	"method": "GET",
	"orderNo": 1729787801019,
	"retryCount": 0,
	"uniqueKey": "https://juejin.cn/post/7389137198782349364",
	"url": "https://juejin.cn/post/7389137198782349364"
}