{
	"id": "XJio2QSbckGurnJ",
	"json": "{\"id\":\"XJio2QSbckGurnJ\",\"url\":\"https://juejin.cn/post/6953405751104634916\",\"uniqueKey\":\"https://juejin.cn/post/6953405751104634916\",\"method\":\"GET\",\"noRetry\":false,\"retryCount\":0,\"errorMessages\":[],\"headers\":{},\"userData\":{\"label\":\"DETAIL\",\"__crawlee\":{\"enqueueStrategy\":\"same-hostname\"}}}",
	"method": "GET",
	"orderNo": 1729787799231,
	"retryCount": 0,
	"uniqueKey": "https://juejin.cn/post/6953405751104634916",
	"url": "https://juejin.cn/post/6953405751104634916"
}