{
	"id": "XqbfNn1YPxcBYtK",
	"json": "{\"id\":\"XqbfNn1YPxcBYtK\",\"url\":\"https://juejin.cn/post/7424028482374500362\",\"loadedUrl\":\"https://juejin.cn/post/7424028482374500362\",\"uniqueKey\":\"https://juejin.cn/post/7424028482374500362\",\"method\":\"GET\",\"noRetry\":false,\"retryCount\":0,\"errorMessages\":[],\"headers\":{},\"userData\":{\"label\":\"DETAIL\",\"__crawlee\":{\"enqueueStrategy\":\"same-hostname\",\"state\":4}},\"handledAt\":\"2024-10-24T18:15:10.074Z\"}",
	"method": "GET",
	"orderNo": null,
	"retryCount": 0,
	"uniqueKey": "https://juejin.cn/post/7424028482374500362",
	"url": "https://juejin.cn/post/7424028482374500362"
}