{
	"id": "Yb9X3NKPOaxuZvw",
	"json": "{\"id\":\"Yb9X3NKPOaxuZvw\",\"url\":\"https://juejin.cn/post/7411343655056850955\",\"uniqueKey\":\"https://juejin.cn/post/7411343655056850955\",\"method\":\"GET\",\"noRetry\":false,\"retryCount\":0,\"errorMessages\":[],\"headers\":{},\"userData\":{\"label\":\"DETAIL\",\"__crawlee\":{\"enqueueStrategy\":\"same-hostname\"}}}",
	"method": "GET",
	"orderNo": 1729787797933,
	"retryCount": 0,
	"uniqueKey": "https://juejin.cn/post/7411343655056850955",
	"url": "https://juejin.cn/post/7411343655056850955"
}