{
  "followeeList": {
    "author": "https://juejin.cn/user/360295542575581",
    "list": [
      {
        "name": "老码小张",
        "avatar": "https://p6-passport.byteacctimg.com/img/user-avatar/cd29b6200992ec3103598ac32d1c31d7~50x50.awebp",
        "href": "https://juejin.cn/user/976022052799405",
        "level": {
          "desc": "No Level",
          "rankNumber": 0
        }
      },
      {
        "name": "Goland猫",
        "avatar": "https://p3-passport.byteacctimg.com/img/user-avatar/c07c29a885101f4f8c8526c82ceea873~50x50.awebp",
        "href": "https://juejin.cn/user/3342976057353992",
        "level": {
          "desc": "No Level",
          "rankNumber": 0
        }
      },
      {
        "name": "攻城师不浪",
        "avatar": "https://p3-passport.byteacctimg.com/img/user-avatar/3b2e10fe13eaf5e173b2c03665da787a~50x50.awebp",
        "href": "https://juejin.cn/user/1697301684048200",
        "level": {
          "desc": "No Level",
          "rankNumber": 0
        }
      },
      {
        "name": "朱哥的掘金",
        "avatar": "https://p3-passport.byteacctimg.com/img/user-avatar/0273c5a10fb486384cef461f8a344d2a~50x50.awebp",
        "href": "https://juejin.cn/user/2201661964034648",
        "level": {
          "desc": "No Level",
          "rankNumber": 0
        }
      },
      {
        "name": "虎妞先生",
        "avatar": "https://p9-passport.byteacctimg.com/img/user-avatar/489331ce9461e22204b28139e5f203bc~50x50.awebp",
        "href": "https://juejin.cn/user/1011206428301774",
        "level": {
          "desc": "No Level",
          "rankNumber": 0
        }
      },
      {
        "name": "shigen01",
        "avatar": "https://p6-passport.byteacctimg.com/img/user-avatar/bac9977faaed870af6f2ededa68bbef3~50x50.awebp",
        "href": "https://juejin.cn/user/3646453196525677",
        "level": {
          "desc": "No Level",
          "rankNumber": 0
        }
      },
      {
        "name": "张拭心",
        "avatar": "https://p3-passport.byteacctimg.com/img/user-avatar/acde3e2b7d3dce7572b63310fbb73898~50x50.awebp",
        "href": "https://juejin.cn/user/571401775094312",
        "level": {
          "desc": "No Level",
          "rankNumber": 0
        }
      },
      {
        "name": "mysteryven",
        "avatar": "https://p26-passport.byteacctimg.com/img/user-avatar/68c2dfca7819a21f4c0d15f6df5a7e48~50x50.awebp",
        "href": "https://juejin.cn/user/430664290155751",
        "level": {
          "desc": "No Level",
          "rankNumber": 0
        }
      },
      {
        "name": "死月",
        "avatar": "https://p26-passport.byteacctimg.com/img/user-avatar/0af3c8f2169193fe203454b63ab664ca~50x50.awebp",
        "href": "https://juejin.cn/user/3614849959735367",
        "level": {
          "desc": "No Level",
          "rankNumber": 0
        }
      },
      {
        "name": "程序员小榆",
        "avatar": "https://p9-passport.byteacctimg.com/img/user-avatar/bb3cbcd319b2eb8cfe0149bb56de259b~50x50.awebp",
        "href": "https://juejin.cn/user/444664871131214",
        "level": {
          "desc": "No Level",
          "rankNumber": 0
        }
      },
      {
        "name": "野生的码农",
        "avatar": "https://p6-passport.byteacctimg.com/img/user-avatar/cd986bfd8cf9cbb772b42ec8c00f144e~50x50.awebp",
        "href": "https://juejin.cn/user/1072714335397869",
        "level": {
          "desc": "No Level",
          "rankNumber": 0
        }
      },
      {
        "name": "mumuy",
        "avatar": "https://p6-passport.byteacctimg.com/img/user-avatar/b946f571b7ba519b58fbdec2cfcc1bbf~50x50.awebp",
        "href": "https://juejin.cn/user/289926798118589",
        "level": {
          "desc": "No Level",
          "rankNumber": 0
        }
      },
      {
        "name": "狂奔滴小马",
        "avatar": "https://p6-passport.byteacctimg.com/img/user-avatar/585e1491713363bc8f67d06c485e8260~50x50.awebp",
        "href": "https://juejin.cn/user/2189882895384093",
        "level": {
          "desc": "No Level",
          "rankNumber": 0
        }
      },
      {
        "name": "余腾靖",
        "avatar": "https://p6-passport.byteacctimg.com/img/user-avatar/b4ad31b0fdc0dac5a51fda622e3e021d~50x50.awebp",
        "href": "https://juejin.cn/user/2664871915684493",
        "level": {
          "desc": "No Level",
          "rankNumber": 0
        }
      },
      {
        "name": "十年踪迹",
        "avatar": "https://p26-passport.byteacctimg.com/img/user-avatar/c2437de949714d0318516d031f27bd86~50x50.awebp",
        "href": "https://juejin.cn/user/712139263189303",
        "level": {
          "desc": "No Level",
          "rankNumber": 0
        }
      },
      {
        "name": "东东拿铁",
        "avatar": "https://p3-passport.byteacctimg.com/img/user-avatar/f684d8f4d550969fabda6a15de0d2a47~50x50.awebp",
        "href": "https://juejin.cn/user/3808364011728392",
        "level": {
          "desc": "No Level",
          "rankNumber": 0
        }
      },
      {
        "name": "泡泡君",
        "avatar": "https://p6-passport.byteacctimg.com/img/user-avatar/2cbe5cd0369e558b6ff9fa73e173537e~50x50.awebp",
        "href": "https://juejin.cn/user/651387678230317",
        "level": {
          "desc": "No Level",
          "rankNumber": 0
        }
      },
      {
        "name": "小颜同学",
        "avatar": "https://p3-passport.byteacctimg.com/img/user-avatar/47989bfd4d731a2b718bb02c56e31680~50x50.awebp",
        "href": "https://juejin.cn/user/1838795983954712",
        "level": {
          "desc": "No Level",
          "rankNumber": 0
        }
      },
      {
        "name": "代码随想录",
        "avatar": "https://p1-jj.byteimg.com/tos-cn-i-t2oaga2asx/gold-user-assets/2020/3/8/170b939240dfb53c~tplv-t2oaga2asx-jj-mark:45:45:0:0:q75.avis",
        "href": "https://juejin.cn/user/4125023360258599",
        "level": {
          "desc": "No Level",
          "rankNumber": 0
        }
      },
      {
        "name": "我不是外星人",
        "avatar": "https://p9-passport.byteacctimg.com/img/user-avatar/3a2345d8f24d7ca454a624d374f37313~50x50.awebp",
        "href": "https://juejin.cn/user/2418581313687390",
        "level": {
          "desc": "No Level",
          "rankNumber": 0
        }
      },
      {
        "name": "杨成功",
        "avatar": "https://p6-passport.byteacctimg.com/img/user-avatar/ce0d388154616b47e913082f936c65fa~50x50.awebp",
        "href": "https://juejin.cn/user/1169536100339101",
        "level": {
          "desc": "No Level",
          "rankNumber": 0
        }
      },
      {
        "name": "前端之虎陈随易",
        "avatar": "https://p9-passport.byteacctimg.com/img/user-avatar/1e53615038b0e9a227c4627ee0bb0a65~50x50.awebp",
        "href": "https://juejin.cn/user/1239904846873326",
        "level": {
          "desc": "No Level",
          "rankNumber": 0
        }
      },
      {
        "name": "前端欧阳",
        "avatar": "https://p3-passport.byteacctimg.com/img/user-avatar/b68f2fe96b5139e2a8ce4e77642207b3~50x50.awebp",
        "href": "https://juejin.cn/user/2885559888654664",
        "level": {
          "desc": "No Level",
          "rankNumber": 0
        }
      },
      {
        "name": "郑鱼咚",
        "avatar": "https://p3-passport.byteacctimg.com/img/user-avatar/5a3703acdec4ac063d1a675e0718863b~50x50.awebp",
        "href": "https://juejin.cn/user/1714893869557512",
        "level": {
          "desc": "No Level",
          "rankNumber": 0
        }
      },
      {
        "name": "冴羽",
        "avatar": "https://p9-passport.byteacctimg.com/img/user-avatar/3cc59c2bbb4a99bcadc06cf1b1e2a4ca~50x50.awebp",
        "href": "https://juejin.cn/user/712139234359182",
        "level": {
          "desc": "No Level",
          "rankNumber": 0
        }
      },
      {
        "name": "为了WLB努力",
        "avatar": "https://p9-passport.byteacctimg.com/img/user-avatar/98e48c913d50a6b6fb51995ee05f6445~50x50.awebp",
        "href": "https://juejin.cn/user/2164315580021310",
        "level": {
          "desc": "No Level",
          "rankNumber": 0
        }
      },
      {
        "name": "程序员凌览",
        "avatar": "https://p9-passport.byteacctimg.com/img/user-avatar/ed76ce42eed371494cacbf22bfb1d3c5~50x50.awebp",
        "href": "https://juejin.cn/user/3350967174565198",
        "level": {
          "desc": "No Level",
          "rankNumber": 0
        }
      },
      {
        "name": "相学长",
        "avatar": "https://p9-passport.byteacctimg.com/img/user-avatar/df053de551c3e21f18453e39f7e656b0~50x50.awebp",
        "href": "https://juejin.cn/user/976022014535230",
        "level": {
          "desc": "No Level",
          "rankNumber": 0
        }
      },
      {
        "name": "石小石Orz",
        "avatar": "https://p3-passport.byteacctimg.com/img/user-avatar/bd431f07728d36167f9c857480f0420b~50x50.awebp",
        "href": "https://juejin.cn/user/660148845294712",
        "level": {
          "desc": "No Level",
          "rankNumber": 0
        }
      },
      {
        "name": "Surmon",
        "avatar": "https://p26-passport.byteacctimg.com/img/user-avatar/76784c8a3c48b434e1f96dcf71d5834e~50x50.awebp",
        "href": "https://juejin.cn/user/289926769282487",
        "level": {
          "desc": "No Level",
          "rankNumber": 0
        }
      },
      {
        "name": "文艺码农天文",
        "avatar": "https://p6-passport.byteacctimg.com/img/user-avatar/ac4a6da321444b7adc6d17e36a00e033~50x50.awebp",
        "href": "https://juejin.cn/user/1433418893900397",
        "level": {
          "desc": "No Level",
          "rankNumber": 0
        }
      },
      {
        "name": "uu_Q",
        "avatar": "https://p9-passport.byteacctimg.com/img/user-avatar/62bfa9658643d1b7490116246145c5b6~50x50.awebp",
        "href": "https://juejin.cn/user/4125023358954526",
        "level": {
          "desc": "No Level",
          "rankNumber": 0
        }
      },
      {
        "name": "可乐鸡翅kele",
        "avatar": "https://p6-passport.byteacctimg.com/img/user-avatar/6c6239b6a28990c389a0cd1eacd7d681~50x50.awebp",
        "href": "https://juejin.cn/user/1028798614353821",
        "level": {
          "desc": "No Level",
          "rankNumber": 0
        }
      },
      {
        "name": "前端大骆",
        "avatar": "https://p3-passport.byteacctimg.com/img/user-avatar/6e4a8f94df51f08f31b0facd7fa92117~50x50.awebp",
        "href": "https://juejin.cn/user/254742429175352",
        "level": {
          "desc": "No Level",
          "rankNumber": 0
        }
      },
      {
        "name": "小九九的爸爸",
        "avatar": "https://p26-passport.byteacctimg.com/img/user-avatar/e45eec524b3d093f5fb3cb0a88c1a26d~50x50.awebp",
        "href": "https://juejin.cn/user/2955079655373319",
        "level": {
          "desc": "No Level",
          "rankNumber": 0
        }
      },
      {
        "name": "古韵",
        "avatar": "https://p3-passport.byteacctimg.com/img/user-avatar/eed2db244754c4b31ccefd471dae2124~50x50.awebp",
        "href": "https://juejin.cn/user/1538972010422872",
        "level": {
          "desc": "No Level",
          "rankNumber": 0
        }
      },
      {
        "name": "飞翔的羊驼",
        "avatar": "https://p3-passport.byteacctimg.com/img/user-avatar/a401733c5c285d8ff7499bbb7ed97b06~50x50.awebp",
        "href": "https://juejin.cn/user/974601950082404",
        "level": {
          "desc": "No Level",
          "rankNumber": 0
        }
      },
      {
        "name": "lyllovelemon",
        "avatar": "https://p3-passport.byteacctimg.com/img/user-avatar/2d62082ef2101134b5ca6f22f357d00a~50x50.awebp",
        "href": "https://juejin.cn/user/4054654615034824",
        "level": {
          "desc": "No Level",
          "rankNumber": 0
        }
      },
      {
        "name": "张鑫旭",
        "avatar": "https://p9-passport.byteacctimg.com/img/user-avatar/68f821ace988798ce6767903eb8731e7~50x50.awebp",
        "href": "https://juejin.cn/user/4089838985290910",
        "level": {
          "desc": "No Level",
          "rankNumber": 0
        }
      },
      {
        "name": "帅地",
        "avatar": "https://p26-passport.byteacctimg.com/img/user-avatar/fbb8e8df610f35b47a41cf24097e62e9~50x50.awebp",
        "href": "https://juejin.cn/user/1468603264145911",
        "level": {
          "desc": "No Level",
          "rankNumber": 0
        }
      },
      {
        "name": "Sunshine_Lin",
        "avatar": "https://p3-passport.byteacctimg.com/img/user-avatar/d71c38d1682c543b33f8d716b3b734ca~50x50.awebp",
        "href": "https://juejin.cn/user/1292681407377624",
        "level": {
          "desc": "No Level",
          "rankNumber": 0
        }
      },
      {
        "name": "元兮",
        "avatar": "https://p9-passport.byteacctimg.com/img/user-avatar/3d143ebe9f309aa35ecf9ac9e9a9b757~50x50.awebp",
        "href": "https://juejin.cn/user/1433418891795806",
        "level": {
          "desc": "No Level",
          "rankNumber": 0
        }
      },
      {
        "name": "前端小付",
        "avatar": "https://p3-passport.byteacctimg.com/img/user-avatar/71804950bb62ed03099dacf3e543c6e0~50x50.awebp",
        "href": "https://juejin.cn/user/2524134427073416",
        "level": {
          "desc": "No Level",
          "rankNumber": 0
        }
      },
      {
        "name": "Story",
        "avatar": "https://p9-passport.byteacctimg.com/img/user-avatar/967ea6c90b5b3e8e53c8e5a9ca8b4b9b~50x50.awebp",
        "href": "https://juejin.cn/user/4011498067205262",
        "level": {
          "desc": "No Level",
          "rankNumber": 0
        }
      },
      {
        "name": "TF男孩",
        "avatar": "https://p9-passport.byteacctimg.com/img/user-avatar/d4c8b3a354aa8066145302332dd1d60c~50x50.awebp",
        "href": "https://juejin.cn/user/615370768790158",
        "level": {
          "desc": "No Level",
          "rankNumber": 0
        }
      },
      {
        "name": "魔术师卡颂",
        "avatar": "https://p26-passport.byteacctimg.com/img/user-avatar/1af004c0850aa09a35522153b4b3cf55~50x50.awebp",
        "href": "https://juejin.cn/user/1943592291009511",
        "level": {
          "desc": "No Level",
          "rankNumber": 0
        }
      },
      {
        "name": "敖丙",
        "avatar": "https://p6-passport.byteacctimg.com/img/user-avatar/7e139da0f373f96b29b3d1c65900a09c~50x50.awebp",
        "href": "https://juejin.cn/user/4406498333825357",
        "level": {
          "desc": "No Level",
          "rankNumber": 0
        }
      },
      {
        "name": "寻找海蓝96",
        "avatar": "https://p9-passport.byteacctimg.com/img/user-avatar/52680db33dd37b7ffb77e373f668a4b7~50x50.awebp",
        "href": "https://juejin.cn/user/3808363978175662",
        "level": {
          "desc": "No Level",
          "rankNumber": 0
        }
      },
      {
        "name": "dailc",
        "avatar": "https://p9-passport.byteacctimg.com/img/user-avatar/a602e2f395e117fb9e8d96bcf29bf03a~50x50.awebp",
        "href": "https://juejin.cn/user/465848659615390",
        "level": {
          "desc": "No Level",
          "rankNumber": 0
        }
      },
      {
        "name": "HollisChuang",
        "avatar": "https://p9-passport.byteacctimg.com/img/user-avatar/c982a49591d66d39f3dce315437c6695~50x50.awebp",
        "href": "https://juejin.cn/user/712139234346894",
        "level": {
          "desc": "No Level",
          "rankNumber": 0
        }
      },
      {
        "name": "旅梦开发团",
        "avatar": "https://p6-passport.byteacctimg.com/img/user-avatar/11174122cb6102aca29ac7599f4e08b4~50x50.awebp",
        "href": "https://juejin.cn/user/2664871913601613",
        "level": {
          "desc": "No Level",
          "rankNumber": 0
        }
      },
      {
        "name": "阳光是sunny",
        "avatar": "https://p3-passport.byteacctimg.com/img/user-avatar/3be8532cb908a794b693f50964f9fe55~50x50.awebp",
        "href": "https://juejin.cn/user/1204720476893064",
        "level": {
          "desc": "No Level",
          "rankNumber": 0
        }
      },
      {
        "name": "程序员鱼皮",
        "avatar": "https://p6-passport.byteacctimg.com/img/user-avatar/70f57170f933eacb9cd6879aea1be4ab~50x50.awebp",
        "href": "https://juejin.cn/user/2444938365386621",
        "level": {
          "desc": "No Level",
          "rankNumber": 0
        }
      },
      {
        "name": "yoUng9527",
        "avatar": "https://p6-passport.byteacctimg.com/img/user-avatar/35d01a216a640224b01d7451437f7fd3~50x50.awebp",
        "href": "https://juejin.cn/user/2383396937141917",
        "level": {
          "desc": "No Level",
          "rankNumber": 0
        }
      },
      {
        "name": "花果山大圣",
        "avatar": "https://p9-passport.byteacctimg.com/img/user-avatar/232746a4fa00cc14150b1dec420018dd~50x50.awebp",
        "href": "https://juejin.cn/user/1556564194370270",
        "level": {
          "desc": "No Level",
          "rankNumber": 0
        }
      },
      {
        "name": "前端双越老师",
        "avatar": "https://p6-passport.byteacctimg.com/img/user-avatar/ed902d900835e2e7e3fdfa57fdeb309b~50x50.awebp",
        "href": "https://juejin.cn/user/1714893868765373",
        "level": {
          "desc": "No Level",
          "rankNumber": 0
        }
      },
      {
        "name": "鑫宝Code",
        "avatar": "https://p9-passport.byteacctimg.com/img/user-avatar/4552f312b94a7b61d766d5c666eadef8~50x50.awebp",
        "href": "https://juejin.cn/user/233547309260286",
        "level": {
          "desc": "No Level",
          "rankNumber": 0
        }
      },
      {
        "name": "徐小夕",
        "avatar": "https://p6-passport.byteacctimg.com/img/user-avatar/d08df4df3fe80db668014b4b815390a5~50x50.awebp",
        "href": "https://juejin.cn/user/3808363978429613",
        "level": {
          "desc": "No Level",
          "rankNumber": 0
        }
      },
      {
        "name": "菲鸽",
        "avatar": "https://p3-passport.byteacctimg.com/img/user-avatar/88bd288485e7e401e21450414b8ec7eb~50x50.awebp",
        "href": "https://juejin.cn/user/3263006241460792",
        "level": {
          "desc": "No Level",
          "rankNumber": 0
        }
      },
      {
        "name": "熊的猫",
        "avatar": "https://p3-passport.byteacctimg.com/img/user-avatar/9cc64189d3fc8b5e82c2af78470da745~50x50.awebp",
        "href": "https://juejin.cn/user/4441682709585128",
        "level": {
          "desc": "No Level",
          "rankNumber": 0
        }
      },
      {
        "name": "谦宇",
        "avatar": "https://p3-passport.byteacctimg.com/img/user-avatar/34daf308526b4f8cee0a19b5c7bc1d31~50x50.awebp",
        "href": "https://juejin.cn/user/443162307720",
        "level": {
          "desc": "No Level",
          "rankNumber": 0
        }
      },
      {
        "name": "Col0ring",
        "avatar": "https://p6-passport.byteacctimg.com/img/user-avatar/e36f91e804eb8a44480d2450bf70b766~50x50.awebp",
        "href": "https://juejin.cn/user/2840793778240253",
        "level": {
          "desc": "No Level",
          "rankNumber": 0
        }
      },
      {
        "name": "sun0day",
        "avatar": "https://p3-passport.byteacctimg.com/img/user-avatar/ac2def0c35059ccb3c522cfb6933912e~50x50.awebp",
        "href": "https://juejin.cn/user/1855631356337032",
        "level": {
          "desc": "No Level",
          "rankNumber": 0
        }
      },
      {
        "name": "zxg_神说要有光",
        "avatar": "https://p9-passport.byteacctimg.com/img/user-avatar/4e9e751e2b32fb8afbbf559a296ccbf2~50x50.awebp",
        "href": "https://juejin.cn/user/2788017216685118",
        "level": {
          "desc": "No Level",
          "rankNumber": 0
        }
      },
      {
        "name": "不要秃头啊",
        "avatar": "https://p26-passport.byteacctimg.com/img/user-avatar/5db9ef9c19e9f3cbbf4fb73e0e283a7a~50x50.awebp",
        "href": "https://juejin.cn/user/932829447855975",
        "level": {
          "desc": "No Level",
          "rankNumber": 0
        }
      },
      {
        "name": "o翔哥o",
        "avatar": "https://p9-passport.byteacctimg.com/img/user-avatar/1089d71b8308999786c384027a61a938~50x50.awebp",
        "href": "https://juejin.cn/user/650530414137534",
        "level": {
          "desc": "No Level",
          "rankNumber": 0
        }
      },
      {
        "name": "网易云音乐技术团队",
        "avatar": "https://p3-passport.byteacctimg.com/img/user-avatar/335727a1f67e82416e203e9516f61273~50x50.awebp",
        "href": "https://juejin.cn/user/4265760847567016",
        "level": {
          "desc": "No Level",
          "rankNumber": 0
        }
      },
      {
        "name": "蒋鹏飞",
        "avatar": "https://p1-jj.byteimg.com/tos-cn-i-t2oaga2asx/gold-user-assets/2020/6/22/172db0de611bd4b0~tplv-t2oaga2asx-jj-mark:45:45:0:0:q75.avis",
        "href": "https://juejin.cn/user/2295436011645655",
        "level": {
          "desc": "No Level",
          "rankNumber": 0
        }
      },
      {
        "name": "txm",
        "avatar": "https://p1-jj.byteimg.com/tos-cn-i-t2oaga2asx/gold-user-assets/2020/3/25/1710fa9d9290023d~tplv-t2oaga2asx-jj-mark:45:45:0:0:q75.avis",
        "href": "https://juejin.cn/user/870468939687661",
        "level": {
          "desc": "No Level",
          "rankNumber": 0
        }
      },
      {
        "name": "蚂蚁集团数据体验技术",
        "avatar": "https://p26-passport.byteacctimg.com/img/user-avatar/1fce0d22c6d5e9097db36db39a52848e~50x50.awebp",
        "href": "https://juejin.cn/user/1486195450988471",
        "level": {
          "desc": "No Level",
          "rankNumber": 0
        }
      },
      {
        "name": "美团点评点餐",
        "avatar": "https://p1-jj.byteimg.com/tos-cn-i-t2oaga2asx/leancloud-assets/8132eeef2c3edd765d6a.jpg~tplv-t2oaga2asx-jj-mark:45:45:0:0:q75.avis",
        "href": "https://juejin.cn/user/4459274890642350",
        "level": {
          "desc": "No Level",
          "rankNumber": 0
        }
      },
      {
        "name": "王仕军",
        "avatar": "https://p3-passport.byteacctimg.com/img/user-avatar/b4aa12d26f82f26b016fb44ac947342c~50x50.awebp",
        "href": "https://juejin.cn/user/4072246758354680",
        "level": {
          "desc": "No Level",
          "rankNumber": 0
        }
      },
      {
        "name": "稀土区",
        "avatar": "https://p1-jj.byteimg.com/tos-cn-i-t2oaga2asx/leancloud-assets/67f53f4569077274f01d.jpg~tplv-t2oaga2asx-jj-mark:45:45:0:0:q75.avis",
        "href": "https://juejin.cn/user/483440844094414",
        "level": {
          "desc": "No Level",
          "rankNumber": 0
        }
      },
      {
        "name": "BobChen",
        "avatar": "https://p6-passport.byteacctimg.com/img/user-avatar/b82a3cf818989bec6bbdcc840312ad61~50x50.awebp",
        "href": "https://juejin.cn/user/1961184472086429",
        "level": {
          "desc": "No Level",
          "rankNumber": 0
        }
      }
    ]
  }
}