{
	"title": "recipe_food_ingredients_adnormal",
	"author": "王宇",
	"publishTime": "一月25,2024",
	"readTime": "12s",
	"tags": "[\"烹饪方案预测语音技能\"]",
	"description": "烹饪方案预测语音技能",
	"article": "*   1[1\\. 插入新数据](#recipe_food_ingredients_adnormal-插入新数据)\n    *   1.1[1.1. 皮蛋](#recipe_food_ingredients_adnormal-皮蛋)\n    *   1.2[1.2. 大于等于50g](#recipe_food_ingredients_adnormal-大于等于50g)\n    *   1.3[1.3. 开水](#recipe_food_ingredients_adnormal-开水)\n*   2[2\\. 3.更新数据](#recipe_food_ingredients_adnormal-3.更新数据)\n*   3[3\\. 4.删除数据（其实是标记为已删除）](#recipe_food_ingredients_adnormal-4.删除数据（其实是标记为已删除）)\n\n1\\. 插入新数据\n=========\n\ntruncate prod\\_vdh\\_model.recipe\\_food\\_ingredients\\_adnormal;\n\n1.1. 皮蛋\n-------\n\n![](/download/attachments/119668741/image2024-1-25_15-15-27.png?version=1&modificationDate=1706166927203&api=v2)\n\n版本：2024-01-25\n\n 展开源码\n\n[expand source](#)[?](#)\n\n`INSERT` `INTO` `prod_vdh_model.recipe_food_ingredients_adnormal (id, classify_name,` `\"content\"``, unit)`\n\n`VALUES``(1079000461510754304,` `'皮蛋'``, 1,` `'个'``),`\n\n`VALUES``(1079721505654800384,` `'皮蛋'``, 1,` `'个'``),`\n\n`VALUES``(1079005224706211840,` `'皮蛋'``, 1,` `'个'``),`\n\n`VALUES``(1078998191340748801,` `'皮蛋'``, 1,` `'个'``);`\n\n1.2. 大于等于50g\n------------\n\n![](/download/attachments/119668741/image2024-1-25_15-15-47.png?version=1&modificationDate=1706166947272&api=v2)\n\n\\--select \\* from recipe\\_food\\_ingredients2 where content >=50 and unit\\_original not in ('g', '克', 'ml', '毫升', '两') and deleted = False\n\n版本：2024-01-25\n\n 展开源码\n\n[expand source](#)[?](#)\n\n`INSERT` `INTO` `prod_vdh_model.recipe_food_ingredients_adnormal (id, classify_name,` `\"content\"``, unit)`\n\n`VALUES``(1077544433342529536,` `'鸡蛋'``, 150,` `'克'``),`\n\n`VALUES``(1077992594944262144,` `'鸡蛋'``, 150,` `'克'``),`\n\n`VALUES``(1079721505654800384,` `'生蚝'``, 150,` `'克'``),`\n\n`VALUES``(1081248042105012224,` `'鸡蛋'``, 130,` `'克'``),`\n\n`VALUES``(1083479619282640898,` `'鸡蛋'``, 110,` `'克'``),`\n\n`VALUES``(1082036533423742977,` `'鸡蛋'``, 150,` `'克'``),`\n\n`VALUES``(1082682191923093505,` `'鸡蛋'``, 100,` `'克'``),`\n\n`VALUES``(1083483296022110210,` `'鸡蛋'``, 110,` `'克'``),`\n\n`VALUES``(1083150877025468418,` `'鸡蛋'``, 150,` `'克'``),`\n\n`VALUES``(1083497663757262848,` `'生蚝'``, 250,` `'克'``),`\n\n`VALUES``(1083846240169861120,` `'鸡蛋'``, 200,` `'克'``),`\n\n`VALUES``(1084128508226543617,` `'鸡蛋'``, 130,` `'克'``),`\n\n`VALUES``(1084775032031780864,` `'鸡蛋'``, 150,` `'克'``),`\n\n`VALUES``(1085197541210300417,` `'鸡蛋'``, 150,` `'克'``),`\n\n`VALUES``(1086258841676513280,` `'生蚝'``, 150,` `'克'``),`\n\n`VALUES``(1086064149336137728,` `'鸡蛋'``, 100,` `'克'``),`\n\n`VALUES``(1086623787454537728,` `'生蚝'``, 70,` `'克'``),`\n\n`VALUES``(1086627355100807168,` `'鸡蛋'``, 200,` `'克'``),`\n\n`VALUES``(1087428139932950529,` `'生蚝'``, 150,` `'克'``),`\n\n`VALUES``(1087802554294181889,` `'鸡蛋'``, 270,` `'克'``),`\n\n`VALUES``(1093892326430502912,` `'鸡腿肉'``, 250,` `'克'``),`\n\n`VALUES``(1096171015490818048,` `'鸡蛋黄'``, 72,` `'克'``),`\n\n`VALUES``(1064488522688692224,` `'鸡'``, 999,` `'克'``),`\n\n`VALUES``(1104078383517863939,` `'纯净水'``, 500,` `'ml'``),`\n\n`VALUES``(1114212769868337152,` `'荔枝'``, 400,` `'克'``),`\n\n`VALUES``(1134112316633403392,` `'鸡蛋'``, 100,` `'克'``),`\n\n`VALUES``(1134140938242732032,` `'生蚝'``, 150,` `'克'``),`\n\n`VALUES``(1139482758273814528,` `'生蚝'``, 150,` `'克'``),`\n\n`VALUES``(1084544922918420481,` `'鸡蛋'``, 50,` `'克'``),`\n\n`VALUES``(1085127190711992320,` `'皮蛋'``, 50,` `'克'``),`\n\n`VALUES``(1085698779756601345,` `'鸡蛋'``, 50,` `'克'``),`\n\n`VALUES``(1064488522705469440,` `'盐'``, 5,` `'克'``),`\n\n`VALUES``(1064488522730635264,` `'鸡蛋'``, 50,` `'克'``),`\n\n`VALUES``(1096071097963147264,` `'鸡蛋'``, 50,` `'克'``),`\n\n1.3. 开水\n-------\n\n\\--select \\* from recipe\\_food\\_ingredients2 where recipe\\_id in (1092460158946451456) and classify\\_name\\_original like '%水%' and deleted = false\n\n版本：2024-01-25\n\n 展开源码\n\n[expand source](#)[?](#)\n\n`INSERT` `INTO` `prod_vdh_model.recipe_food_ingredients_adnormal (id, classify_name,` `\"content\"``, unit)`\n\n`VALUES``(1092475806758019074,` `'开水'``, 200,` `'克'``),`\n\n`VALUES``(1094921150380974081,` `'开水'``, 260,` `'克'``),`\n\n`VALUES``(1123930999368540162,` `'开水'``, 300,` `'克'``),`\n\n`VALUES``(1097895237745430529,` `'开水'``, 100,` `'克'``),`\n\n`VALUES``(1103624554225270785,` `'开水'``, 60,` `'克'``),`\n\n`VALUES``(1103689538993061888,` `'开水'``, 600,` `'克'``),`\n\n`VALUES``(1123938326556418052,` `'开水'``, 600,` `'克'``),`\n\n`VALUES``(1113470103169708033,` `'开水'``, 250,` `'克'``),`\n\n`VALUES``(1107991758764965888,` `'开水'``, 500,` `'克'``),`\n\n`VALUES``(1123931587598704645,` `'开水'``, 300,` `'克'``),`\n\n`VALUES``(1097905121652166657,` `'开水'``, 300,` `'克'``),`\n\n`VALUES``(1097905363431915521,` `'开水'``, 600,` `'克'``),`\n\n`VALUES``(1123928051674603521,` `'开水'``, 500,` `'克'``),`\n\n`VALUES``(1103607704003215362,` `'开水'``, 200,` `'克'``),`\n\n`VALUES``(1103609302872297472,` `'开水'``, 600,` `'克'``),`\n\n`VALUES``(1103615712704139264,` `'开水'``, 750,` `'克'``),`\n\n`VALUES``(1106620513985167361,` `'开水'``, 100,` `'克'``),`\n\n`VALUES``(1106610039692791810,` `'开水'``, 60,` `'克'``),`\n\n`VALUES``(1107974909193027585,` `'开水'``, 120,` `'克'``),`\n\n`VALUES``(1080529454989672449,` `'开水'``, 230,` `'克'``),`\n\n`VALUES``(1080530914565521408,` `'开水'``, 230,` `'克'``);`\n\n2\\. 3.更新数据\n==========\n\nUPDATE prod\\_vdh\\_model.recipe\\_food\\_ingredients\\_adnormal\n\nset modify\\_time=CURRENT\\_TIMESTAMP, classify\\_name='', \"content\"=0, unit='', status=2 WHERE id=0;\n\n3\\. 4.删除数据（其实是标记为已删除）\n=====================\n\nUPDATE prod\\_vdh\\_model.recipe\\_food\\_ingredients\\_adnormal\n\nset modify\\_time=CURRENT\\_TIMESTAMP, deleted\\=true\n\nWHERE id=0;\n\n[Filter table data](#)[Create a pivot table](#)[Create a chart from data series](#)\n\n[Configure buttons visibility](/users/tfac-settings.action)"
}