{
	"id": "LmTClPDc6hUUa52",
	"json": "{\"id\":\"LmTClPDc6hUUa52\",\"url\":\"https://wiki.yingzi.com/pages/viewpage.action?pageId=97897887\",\"uniqueKey\":\"https://wiki.yingzi.com/pages/viewpage.action?pageId=97897887\",\"method\":\"GET\",\"noRetry\":false,\"retryCount\":0,\"errorMessages\":[],\"headers\":{},\"userData\":{\"label\":\"DETAIL\",\"__crawlee\":{\"enqueueStrategy\":\"same-hostname\"}}}",
	"method": "GET",
	"orderNo": 1728325775160,
	"retryCount": 0,
	"uniqueKey": "https://wiki.yingzi.com/pages/viewpage.action?pageId=97897887",
	"url": "https://wiki.yingzi.com/pages/viewpage.action?pageId=97897887"
}