{
	"id": "PygFJO1RbPFZbVh",
	"json": "{\"id\":\"PygFJO1RbPFZbVh\",\"url\":\"https://wiki.yingzi.com/pages/viewpage.action?pageId=97902762\",\"uniqueKey\":\"https://wiki.yingzi.com/pages/viewpage.action?pageId=97902762\",\"method\":\"GET\",\"noRetry\":false,\"retryCount\":0,\"errorMessages\":[],\"headers\":{},\"userData\":{\"label\":\"DETAIL\",\"__crawlee\":{\"enqueueStrategy\":\"same-hostname\"}}}",
	"method": "GET",
	"orderNo": 1728325776155,
	"retryCount": 0,
	"uniqueKey": "https://wiki.yingzi.com/pages/viewpage.action?pageId=97902762",
	"url": "https://wiki.yingzi.com/pages/viewpage.action?pageId=97902762"
}