{
	"id": "VKhkvXKm87dKxtf",
	"json": "{\"id\":\"VKhkvXKm87dKxtf\",\"url\":\"https://wiki.yingzi.com/pages/viewpage.action?pageId=91142885\",\"loadedUrl\":\"https://wiki.yingzi.com/pages/viewpage.action?pageId=91142885\",\"uniqueKey\":\"https://wiki.yingzi.com/pages/viewpage.action?pageId=91142885\",\"method\":\"GET\",\"noRetry\":false,\"retryCount\":0,\"errorMessages\":[],\"headers\":{},\"userData\":{\"label\":\"DETAIL\",\"__crawlee\":{\"enqueueStrategy\":\"same-hostname\",\"state\":4}},\"handledAt\":\"2024-10-07T18:40:08.929Z\"}",
	"method": "GET",
	"orderNo": null,
	"retryCount": 0,
	"uniqueKey": "https://wiki.yingzi.com/pages/viewpage.action?pageId=91142885",
	"url": "https://wiki.yingzi.com/pages/viewpage.action?pageId=91142885"
}