{
	"id": "WPPn7zMUqGbqPg7",
	"json": "{\"id\":\"WPPn7zMUqGbqPg7\",\"url\":\"https://wiki.yingzi.com/pages/viewpage.action?pageId=86772719\",\"uniqueKey\":\"https://wiki.yingzi.com/pages/viewpage.action?pageId=86772719\",\"method\":\"GET\",\"noRetry\":false,\"retryCount\":0,\"errorMessages\":[],\"headers\":{},\"userData\":{\"label\":\"DETAIL\",\"__crawlee\":{\"enqueueStrategy\":\"same-hostname\"}}}",
	"method": "GET",
	"orderNo": 1728325776017,
	"retryCount": 0,
	"uniqueKey": "https://wiki.yingzi.com/pages/viewpage.action?pageId=86772719",
	"url": "https://wiki.yingzi.com/pages/viewpage.action?pageId=86772719"
}