{
	"id": "K71lk1Y7LXgIhfA",
	"json": "{\"id\":\"K71lk1Y7LXgIhfA\",\"url\":\"https://juejin.cn/post/7418091393967046682\",\"loadedUrl\":\"https://juejin.cn/post/7418091393967046682\",\"uniqueKey\":\"https://juejin.cn/post/7418091393967046682\",\"method\":\"GET\",\"noRetry\":false,\"retryCount\":1,\"errorMessages\":[\"Error: requestHandler timed out after 60 seconds.\\n    at Timeout._onTimeout (D:\\\\gitlab\\\\myBlogPaperMod\\\\node_modules\\\\@apify\\\\timeout\\\\cjs\\\\index.cjs:64:68)\\n    at listOnTimeout (node:internal/timers:581:17)\\n    at process.processTimers (node:internal/timers:519:7)\"],\"headers\":{},\"userData\":{\"label\":\"DETAIL\",\"__crawlee\":{\"enqueueStrategy\":\"same-hostname\",\"state\":4}},\"handledAt\":\"2024-09-26T09:21:17.333Z\"}",
	"method": "GET",
	"orderNo": null,
	"retryCount": 1,
	"uniqueKey": "https://juejin.cn/post/7418091393967046682",
	"url": "https://juejin.cn/post/7418091393967046682"
}