{
	"id": "rVV8LOrLc3XJAbn",
	"json": "{\"id\":\"rVV8LOrLc3XJAbn\",\"url\":\"https://juejin.cn/post/7340167256268390436\",\"uniqueKey\":\"https://juejin.cn/post/7340167256268390436\",\"method\":\"GET\",\"noRetry\":false,\"retryCount\":0,\"errorMessages\":[],\"headers\":{},\"userData\":{\"label\":\"DETAIL\",\"__crawlee\":{\"enqueueStrategy\":\"same-hostname\"}}}",
	"method": "GET",
	"orderNo": 1727313120073,
	"retryCount": 0,
	"uniqueKey": "https://juejin.cn/post/7340167256268390436",
	"url": "https://juejin.cn/post/7340167256268390436"
}